Workbook
Name aporte: APP!$D$17
Name patrimonio: APP!$D$20
Name qtd_anos: APP!$D$18
Name rendimento_carteira: APP!$D$13
Name taxa_mensal: APP!$D$19

Sheet APP
B11: CONFIGURAÇÕES
B12: Salário | D12: 500
B13: Rendimento Carteira | D13: 0.01
B14: Sugestão de Investimento (30%) | D14: =D12*30% -> 150
B16: INVESTIMENTO MENSAL
B17: Quanto investir por mês ? | D17: 800
B18: Por Quantos Anos ? | D18: 5
B19: Taxa de Rendimento mensal ? | D19: 0.0108
B20: Patrimônio acumulado ? | D20: =FV(taxa_mensal,+qtd_anos*12,aporte)*-1 -> 67043.215
B21: Dividendos Mensais ? | D21: =patrimonio*taxa_mensal -> 724.06673
B23: CENÁRIOS | D23: DIVIDENDOS
A24: 2 | B24: Quanto em 2 Anos ? | C24: =FV($D$19,$A24*12,$D$17)*-1 -> 21784.691 | D24: =C24*taxa_mensal -> 235.27466
A25: 5 | B25: Quanto em 5 Anos ? | C25: =FV($D$19,$A25*12,$D$17)*-1 -> 67043.215 | D25: =C25*taxa_mensal -> 724.06673
A26: 10 | B26: Quanto em 10 Anos ? | C26: =FV($D$19,$A26*12,$D$17)*-1 -> 194766.13 | D26: =C26*taxa_mensal -> 2103.4742
A27: 20 | B27: Quanto em 20 Anos ? | C27: =FV($D$19,$A27*12,$D$17)*-1 -> 901639.19 | D27: =C27*taxa_mensal -> 9737.7033
A28: 30 | B28: Quanto em 30 Anos ? | C28: =FV($D$19,$A28*12,$D$17)*-1 -> 3467123.8 | D28: =C28*taxa_mensal -> 37444.938
B32: PERFIL | C32: Agressivo
B33: VALOR A SER INVESTIDO POR MÊS | D33: 800
B35: TIPO DE FII | C35: Percentual Sugerido | D35: Valores
B36: PAPEL | C36: =VLOOKUP($C$32&"-"&B36,Planilha1!$A:$D,4,FALSE) -> 0.5 | D36: =C36*$D$33 -> 400
B37: TIJOLO | C37: =VLOOKUP($C$32&"-"&B37,Planilha1!$A:$D,4,FALSE) -> 0.1 | D37: =C37*$D$33 -> 80
B38: HÍBRIDOS | C38: =VLOOKUP($C$32&"-"&B38,Planilha1!$A:$D,4,FALSE) -> 0.05 | D38: =C38*$D$33 -> 40
B39: FOFs | C39: =VLOOKUP($C$32&"-"&B39,Planilha1!$A:$D,4,FALSE) -> 0.05 | D39: =C39*$D$33 -> 40
B40: DESENVOLVIMENTO | C40: =VLOOKUP($C$32&"-"&B40,Planilha1!$A:$D,4,FALSE) -> 0.2 | D40: =C40*$D$33 -> 160
B41: HOTELARIAS | C41: =VLOOKUP($C$32&"-"&B41,Planilha1!$A:$D,4,FALSE) -> 0.1 | D41: =C41*$D$33 -> 80
B42: valor total | D42: =SUM(D36:D41) -> 800

Sheet Planilha1
A1: CHAVE | B1: PERFIL | C1: TIPO DE FII | D1: PORCENTAGEM %
A2: =B2&"-"&C2 -> Conservador-PAPEL | B2: Conservador | C2: PAPEL | D2: 0.3
A3: =B3&"-"&C3 -> Conservador-TIJOLO | B3: Conservador | C3: TIJOLO | D3: 0.5
A4: =B4&"-"&C4 -> Conservador-HÍBRIDOS | B4: Conservador | C4: HÍBRIDOS | D4: 0.1 | F4: MODERADO-TIJOLO | G4: =VLOOKUP(F4,$A:$D,4,FALSE) -> 0.35
A5: =B5&"-"&C5 -> Conservador-FOFs | B5: Conservador | C5: FOFs | D5: 0.1
A6: =B6&"-"&C6 -> Conservador-DESENVOLVIMENTO | B6: Conservador | C6: DESENVOLVIMENTO | D6: 0
A7: =B7&"-"&C7 -> Conservador-HOTELARIAS | B7: Conservador | C7: HOTELARIAS | D7: 0
A8: =B8&"-"&C8 -> Moderado-PAPEL | B8: Moderado | C8: PAPEL | D8: 0.32
A9: =B9&"-"&C9 -> Moderado-TIJOLO | B9: Moderado | C9: TIJOLO | D9: 0.35
A10: =B10&"-"&C10 -> Moderado-HÍBRIDOS | B10: Moderado | C10: HÍBRIDOS | D10: 0.08
A11: =B11&"-"&C11 -> Moderado-FOFs | B11: Moderado | C11: FOFs | D11: 0.05
A12: =B12&"-"&C12 -> Moderado-DESENVOLVIMENTO | B12: Moderado | C12: DESENVOLVIMENTO | D12: 0.1
A13: =B13&"-"&C13 -> Moderado-HOTELARIAS | B13: Moderado | C13: HOTELARIAS | D13: 0.1
A14: =B14&"-"&C14 -> Agressivo-PAPEL | B14: Agressivo | C14: PAPEL | D14: 0.5
A15: =B15&"-"&C15 -> Agressivo-TIJOLO | B15: Agressivo | C15: TIJOLO | D15: 0.1
A16: =B16&"-"&C16 -> Agressivo-HÍBRIDOS | B16: Agressivo | C16: HÍBRIDOS | D16: 0.05
... A19: =B19&"-"&C19 -> Agressivo-HOTELARIAS | B19: Agressivo | C19: HOTELARIAS | D19: 0.1
